pathxf/__init__.py
pathxf/app.py
pathxf/bids.py
pathxf/spec.py
pathxf/utils.py
pathxf-0.0.3.dist-info/METADATA
pathxf-0.0.3.dist-info/WHEEL
pathxf-0.0.3.dist-info/entry_points.txt
pathxf-0.0.3.dist-info/RECORD
