Metadata-Version: 2.1
Name: pathxf
Version: 0.0.3
Summary: 
Author: Peter Van Dyken
Author-email: pvandyk2@uwo.ca
Requires-Python: >=3.9,<3.12
Classifier: Programming Language :: Python :: 3
Classifier: Programming Language :: Python :: 3.9
Classifier: Programming Language :: Python :: 3.10
Classifier: Programming Language :: Python :: 3.11
Requires-Dist: appdirs (>=1.4.4,<2.0.0)
Requires-Dist: more-itertools (>=9.0,<10.0)
Requires-Dist: pyyaml (>=6.0,<7.0)
Requires-Dist: typer (>=0.7.0,<0.8.0)
Requires-Dist: typing-extensions (>=4.5.0,<5.0.0)
